{
  "statistics_by_year": [
    {
      "Year": 2018,
      "Team": "philadelphia-eagles",
      "receiving_gamesPlayed": "7",
      "receiving_receptions": "20",
      "receiving_receivingTargets": "23",
      "receiving_receivingYards": "195",
      "receiving_yardsPerReception": "9.8",
      "receiving_receivingTouchdowns": "0",
      "receiving_longReception": "50",
      "receiving_receivingFirstDowns": "9",
      "receiving_receivingFumbles": "1",
      "receiving_receivingFumblesLost": "0",
      "rushing_gamesPlayed": "7",
      "rushing_rushingAttempts": "1",
      "rushing_rushingYards": "7",
      "rushing_yardsPerRushAttempt": "7.0",
      "rushing_rushingTouchdowns": "0",
      "rushing_longRushing": "7",
      "rushing_rushingFirstDowns": "0",
      "rushing_rushingFumbles": "0",
      "rushing_rushingFumblesLost": "0",
      "passing_gamesPlayed": "7",
      "passing_completions": "0",
      "passing_passingAttempts": "0",
      "passing_completionPct": "0.0",
      "passing_passingYards": "0",
      "passing_yardsPerPassAttempt": "0.0",
      "passing_passingTouchdowns": "0",
      "passing_interceptions": "0",
      "passing_longPassing": "0",
      "passing_sacks": "0",
      "passing_QBRating": "39.6",
      "passing_adjQBR": "-",
      "returning_gamesPlayed": "7",
      "returning_puntReturns": "16",
      "returning_puntReturnYards": "146",
      "returning_puntReturnTouchdowns": "0",
      "returning_puntReturnFairCatches": "8",
      "returning_longPuntReturn": "30",
      "returning_kickReturns": "9",
      "returning_kickReturnYards": "221",
      "returning_kickReturnTouchdowns": "0",
      "returning_kickReturnFairCatches": "0",
      "returning_longKickReturn": "30",
      "defensive_gamesPlayed": "N/A",
      "defensive_totalTackles": "N/A",
      "defensive_soloTackles": "N/A",
      "defensive_assistTackles": "N/A",
      "defensive_sacks": "N/A",
      "defensive_fumblesForced": "N/A",
      "defensive_fumblesRecovered": "N/A",
      "defensive_fumblesRecoveredYards": "N/A",
      "defensive_interceptions": "N/A",
      "defensive_interceptionYards": "N/A",
      "defensive_avgInterceptionYards": "N/A",
      "defensive_interceptionTouchdowns": "N/A",
      "defensive_longInterception": "N/A",
      "defensive_passesDefended": "N/A",
      "defensive_stuffs": "N/A",
      "defensive_stuffYards": "N/A",
      "defensive_kicksBlocked": "N/A",
      "scoring_gamesPlayed": "N/A",
      "scoring_passingTouchdowns": "N/A",
      "scoring_rushingTouchdowns": "N/A",
      "scoring_receivingTouchdowns": "N/A",
      "scoring_returnTouchdowns": "N/A",
      "scoring_totalTouchdowns": "N/A",
      "scoring_totalTwoPointConvs": "N/A",
      "scoring_kickExtraPoints": "N/A",
      "scoring_fieldGoals": "N/A",
      "scoring_totalPoints": "N/A",
      "kicking_gamesPlayed": "N/A",
      "kicking_fieldGoalsMade-fieldGoalAttempts": "N/A",
      "kicking_fieldGoalPct": "N/A",
      "kicking_fieldGoalsMade1_19-fieldGoalAttempts1_19": "N/A",
      "kicking_fieldGoalsMade20_29-fieldGoalAttempts20_29": "N/A",
      "kicking_fieldGoalsMade30_39-fieldGoalAttempts30_39": "N/A",
      "kicking_fieldGoalsMade40_49-fieldGoalAttempts40_49": "N/A",
      "kicking_fieldGoalsMade50-fieldGoalAttempts50": "N/A",
      "kicking_longFieldGoalMade": "N/A",
      "kicking_extraPointsMade": "N/A",
      "kicking_extraPointAttempts": "N/A",
      "kicking_totalKickingPoints": "N/A"
    },
    {
      "Year": 2019,
      "Team": "houston-texans",
      "receiving_gamesPlayed": "16",
      "receiving_receptions": "11",
      "receiving_receivingTargets": "14",
      "receiving_receivingYards": "162",
      "receiving_yardsPerReception": "14.7",
      "receiving_receivingTouchdowns": "0",
      "receiving_longReception": "46",
      "receiving_receivingFirstDowns": "6",
      "receiving_receivingFumbles": "0",
      "receiving_receivingFumblesLost": "0",
      "rushing_gamesPlayed": "N/A",
      "rushing_rushingAttempts": "N/A",
      "rushing_rushingYards": "N/A",
      "rushing_yardsPerRushAttempt": "N/A",
      "rushing_rushingTouchdowns": "N/A",
      "rushing_longRushing": "N/A",
      "rushing_rushingFirstDowns": "N/A",
      "rushing_rushingFumbles": "N/A",
      "rushing_rushingFumblesLost": "N/A",
      "passing_gamesPlayed": "16",
      "passing_completions": "0",
      "passing_passingAttempts": "0",
      "passing_completionPct": "0.0",
      "passing_passingYards": "0",
      "passing_yardsPerPassAttempt": "0.0",
      "passing_passingTouchdowns": "0",
      "passing_interceptions": "0",
      "passing_longPassing": "0",
      "passing_sacks": "0",
      "passing_QBRating": "39.6",
      "passing_adjQBR": "-",
      "returning_gamesPlayed": "16",
      "returning_puntReturns": "22",
      "returning_puntReturnYards": "214",
      "returning_puntReturnTouchdowns": "0",
      "returning_puntReturnFairCatches": "18",
      "returning_longPuntReturn": "23",
      "returning_kickReturns": "14",
      "returning_kickReturnYards": "308",
      "returning_kickReturnTouchdowns": "0",
      "returning_kickReturnFairCatches": "0",
      "returning_longKickReturn": "31",
      "defensive_gamesPlayed": "N/A",
      "defensive_totalTackles": "N/A",
      "defensive_soloTackles": "N/A",
      "defensive_assistTackles": "N/A",
      "defensive_sacks": "N/A",
      "defensive_fumblesForced": "N/A",
      "defensive_fumblesRecovered": "N/A",
      "defensive_fumblesRecoveredYards": "N/A",
      "defensive_interceptions": "N/A",
      "defensive_interceptionYards": "N/A",
      "defensive_avgInterceptionYards": "N/A",
      "defensive_interceptionTouchdowns": "N/A",
      "defensive_longInterception": "N/A",
      "defensive_passesDefended": "N/A",
      "defensive_stuffs": "N/A",
      "defensive_stuffYards": "N/A",
      "defensive_kicksBlocked": "N/A",
      "scoring_gamesPlayed": "N/A",
      "scoring_passingTouchdowns": "N/A",
      "scoring_rushingTouchdowns": "N/A",
      "scoring_receivingTouchdowns": "N/A",
      "scoring_returnTouchdowns": "N/A",
      "scoring_totalTouchdowns": "N/A",
      "scoring_totalTwoPointConvs": "N/A",
      "scoring_kickExtraPoints": "N/A",
      "scoring_fieldGoals": "N/A",
      "scoring_totalPoints": "N/A",
      "kicking_gamesPlayed": "N/A",
      "kicking_fieldGoalsMade-fieldGoalAttempts": "N/A",
      "kicking_fieldGoalPct": "N/A",
      "kicking_fieldGoalsMade1_19-fieldGoalAttempts1_19": "N/A",
      "kicking_fieldGoalsMade20_29-fieldGoalAttempts20_29": "N/A",
      "kicking_fieldGoalsMade30_39-fieldGoalAttempts30_39": "N/A",
      "kicking_fieldGoalsMade40_49-fieldGoalAttempts40_49": "N/A",
      "kicking_fieldGoalsMade50-fieldGoalAttempts50": "N/A",
      "kicking_longFieldGoalMade": "N/A",
      "kicking_extraPointsMade": "N/A",
      "kicking_extraPointAttempts": "N/A",
      "kicking_totalKickingPoints": "N/A"
    },
    {
      "Year": 2020,
      "Team": "houston-texans",
      "receiving_gamesPlayed": "9",
      "receiving_receptions": "1",
      "receiving_receivingTargets": "2",
      "receiving_receivingYards": "8",
      "receiving_yardsPerReception": "8.0",
      "receiving_receivingTouchdowns": "0",
      "receiving_longReception": "8",
      "receiving_receivingFirstDowns": "0",
      "receiving_receivingFumbles": "0",
      "receiving_receivingFumblesLost": "0",
      "rushing_gamesPlayed": "N/A",
      "rushing_rushingAttempts": "N/A",
      "rushing_rushingYards": "N/A",
      "rushing_yardsPerRushAttempt": "N/A",
      "rushing_rushingTouchdowns": "N/A",
      "rushing_longRushing": "N/A",
      "rushing_rushingFirstDowns": "N/A",
      "rushing_rushingFumbles": "N/A",
      "rushing_rushingFumblesLost": "N/A",
      "passing_gamesPlayed": "4",
      "passing_completions": "0",
      "passing_passingAttempts": "0",
      "passing_completionPct": "0.0",
      "passing_passingYards": "0",
      "passing_yardsPerPassAttempt": "0.0",
      "passing_passingTouchdowns": "0",
      "passing_interceptions": "0",
      "passing_longPassing": "0",
      "passing_sacks": "0",
      "passing_QBRating": "39.6",
      "passing_adjQBR": "-",
      "returning_gamesPlayed": "4",
      "returning_puntReturns": "4",
      "returning_puntReturnYards": "30",
      "returning_puntReturnTouchdowns": "0",
      "returning_puntReturnFairCatches": "7",
      "returning_longPuntReturn": "13",
      "returning_kickReturns": "0",
      "returning_kickReturnYards": "0",
      "returning_kickReturnTouchdowns": "0",
      "returning_kickReturnFairCatches": "0",
      "returning_longKickReturn": "0",
      "defensive_gamesPlayed": "N/A",
      "defensive_totalTackles": "N/A",
      "defensive_soloTackles": "N/A",
      "defensive_assistTackles": "N/A",
      "defensive_sacks": "N/A",
      "defensive_fumblesForced": "N/A",
      "defensive_fumblesRecovered": "N/A",
      "defensive_fumblesRecoveredYards": "N/A",
      "defensive_interceptions": "N/A",
      "defensive_interceptionYards": "N/A",
      "defensive_avgInterceptionYards": "N/A",
      "defensive_interceptionTouchdowns": "N/A",
      "defensive_longInterception": "N/A",
      "defensive_passesDefended": "N/A",
      "defensive_stuffs": "N/A",
      "defensive_stuffYards": "N/A",
      "defensive_kicksBlocked": "N/A",
      "scoring_gamesPlayed": "N/A",
      "scoring_passingTouchdowns": "N/A",
      "scoring_rushingTouchdowns": "N/A",
      "scoring_receivingTouchdowns": "N/A",
      "scoring_returnTouchdowns": "N/A",
      "scoring_totalTouchdowns": "N/A",
      "scoring_totalTwoPointConvs": "N/A",
      "scoring_kickExtraPoints": "N/A",
      "scoring_fieldGoals": "N/A",
      "scoring_totalPoints": "N/A",
      "kicking_gamesPlayed": "N/A",
      "kicking_fieldGoalsMade-fieldGoalAttempts": "N/A",
      "kicking_fieldGoalPct": "N/A",
      "kicking_fieldGoalsMade1_19-fieldGoalAttempts1_19": "N/A",
      "kicking_fieldGoalsMade20_29-fieldGoalAttempts20_29": "N/A",
      "kicking_fieldGoalsMade30_39-fieldGoalAttempts30_39": "N/A",
      "kicking_fieldGoalsMade40_49-fieldGoalAttempts40_49": "N/A",
      "kicking_fieldGoalsMade50-fieldGoalAttempts50": "N/A",
      "kicking_longFieldGoalMade": "N/A",
      "kicking_extraPointsMade": "N/A",
      "kicking_extraPointAttempts": "N/A",
      "kicking_totalKickingPoints": "N/A"
    },
    {
      "Year": 2021,
      "Team": "washington",
      "receiving_gamesPlayed": "17",
      "receiving_receptions": "24",
      "receiving_receivingTargets": "44",
      "receiving_receivingYards": "296",
      "receiving_yardsPerReception": "12.3",
      "receiving_receivingTouchdowns": "3",
      "receiving_longReception": "26",
      "receiving_receivingFirstDowns": "17",
      "receiving_receivingFumbles": "0",
      "receiving_receivingFumblesLost": "0",
      "rushing_gamesPlayed": "17",
      "rushing_rushingAttempts": "10",
      "rushing_rushingYards": "89",
      "rushing_yardsPerRushAttempt": "8.9",
      "rushing_rushingTouchdowns": "0",
      "rushing_longRushing": "27",
      "rushing_rushingFirstDowns": "4",
      "rushing_rushingFumbles": "1",
      "rushing_rushingFumblesLost": "0",
      "passing_gamesPlayed": "17",
      "passing_completions": "0",
      "passing_passingAttempts": "0",
      "passing_completionPct": "0.0",
      "passing_passingYards": "0",
      "passing_yardsPerPassAttempt": "0.0",
      "passing_passingTouchdowns": "0",
      "passing_interceptions": "0",
      "passing_longPassing": "0",
      "passing_sacks": "0",
      "passing_QBRating": "39.6",
      "passing_adjQBR": "-",
      "returning_gamesPlayed": "17",
      "returning_puntReturns": "16",
      "returning_puntReturnYards": "134",
      "returning_puntReturnTouchdowns": "0",
      "returning_puntReturnFairCatches": "19",
      "returning_longPuntReturn": "16",
      "returning_kickReturns": "36",
      "returning_kickReturnYards": "904",
      "returning_kickReturnTouchdowns": "1",
      "returning_kickReturnFairCatches": "0",
      "returning_longKickReturn": "101",
      "defensive_gamesPlayed": "17",
      "defensive_totalTackles": "2",
      "defensive_soloTackles": "2",
      "defensive_assistTackles": "0",
      "defensive_sacks": "0",
      "defensive_fumblesForced": "0",
      "defensive_fumblesRecovered": "0",
      "defensive_fumblesRecoveredYards": "0",
      "defensive_interceptions": "0",
      "defensive_interceptionYards": "0",
      "defensive_avgInterceptionYards": "0.0",
      "defensive_interceptionTouchdowns": "0",
      "defensive_longInterception": "0",
      "defensive_passesDefended": "0",
      "defensive_stuffs": "0",
      "defensive_stuffYards": "0",
      "defensive_kicksBlocked": "0",
      "scoring_gamesPlayed": "17",
      "scoring_passingTouchdowns": "0",
      "scoring_rushingTouchdowns": "0",
      "scoring_receivingTouchdowns": "3",
      "scoring_returnTouchdowns": "1",
      "scoring_totalTouchdowns": "4",
      "scoring_totalTwoPointConvs": "0",
      "scoring_kickExtraPoints": "0",
      "scoring_fieldGoals": "0",
      "scoring_totalPoints": "24",
      "kicking_gamesPlayed": "N/A",
      "kicking_fieldGoalsMade-fieldGoalAttempts": "N/A",
      "kicking_fieldGoalPct": "N/A",
      "kicking_fieldGoalsMade1_19-fieldGoalAttempts1_19": "N/A",
      "kicking_fieldGoalsMade20_29-fieldGoalAttempts20_29": "N/A",
      "kicking_fieldGoalsMade30_39-fieldGoalAttempts30_39": "N/A",
      "kicking_fieldGoalsMade40_49-fieldGoalAttempts40_49": "N/A",
      "kicking_fieldGoalsMade50-fieldGoalAttempts50": "N/A",
      "kicking_longFieldGoalMade": "N/A",
      "kicking_extraPointsMade": "N/A",
      "kicking_extraPointAttempts": "N/A",
      "kicking_totalKickingPoints": "N/A"
    },
    {
      "Year": 2022,
      "Team": "los-angeles-chargers",
      "receiving_gamesPlayed": "17",
      "receiving_receptions": "46",
      "receiving_receivingTargets": "65",
      "receiving_receivingYards": "538",
      "receiving_yardsPerReception": "11.7",
      "receiving_receivingTouchdowns": "3",
      "receiving_longReception": "35",
      "receiving_receivingFirstDowns": "29",
      "receiving_receivingFumbles": "1",
      "receiving_receivingFumblesLost": "1",
      "rushing_gamesPlayed": "17",
      "rushing_rushingAttempts": "2",
      "rushing_rushingYards": "-15",
      "rushing_yardsPerRushAttempt": "-7.5",
      "rushing_rushingTouchdowns": "0",
      "rushing_longRushing": "-5",
      "rushing_rushingFirstDowns": "0",
      "rushing_rushingFumbles": "0",
      "rushing_rushingFumblesLost": "0",
      "passing_gamesPlayed": "17",
      "passing_completions": "0",
      "passing_passingAttempts": "0",
      "passing_completionPct": "0.0",
      "passing_passingYards": "0",
      "passing_yardsPerPassAttempt": "0.0",
      "passing_passingTouchdowns": "0",
      "passing_interceptions": "0",
      "passing_longPassing": "0",
      "passing_sacks": "0",
      "passing_QBRating": "39.6",
      "passing_adjQBR": "-",
      "returning_gamesPlayed": "17",
      "returning_puntReturns": "29",
      "returning_puntReturnYards": "339",
      "returning_puntReturnTouchdowns": "0",
      "returning_puntReturnFairCatches": "17",
      "returning_longPuntReturn": "28",
      "returning_kickReturns": "26",
      "returning_kickReturnYards": "497",
      "returning_kickReturnTouchdowns": "0",
      "returning_kickReturnFairCatches": "0",
      "returning_longKickReturn": "33",
      "defensive_gamesPlayed": "N/A",
      "defensive_totalTackles": "N/A",
      "defensive_soloTackles": "N/A",
      "defensive_assistTackles": "N/A",
      "defensive_sacks": "N/A",
      "defensive_fumblesForced": "N/A",
      "defensive_fumblesRecovered": "N/A",
      "defensive_fumblesRecoveredYards": "N/A",
      "defensive_interceptions": "N/A",
      "defensive_interceptionYards": "N/A",
      "defensive_avgInterceptionYards": "N/A",
      "defensive_interceptionTouchdowns": "N/A",
      "defensive_longInterception": "N/A",
      "defensive_passesDefended": "N/A",
      "defensive_stuffs": "N/A",
      "defensive_stuffYards": "N/A",
      "defensive_kicksBlocked": "N/A",
      "scoring_gamesPlayed": "17",
      "scoring_passingTouchdowns": "0",
      "scoring_rushingTouchdowns": "0",
      "scoring_receivingTouchdowns": "3",
      "scoring_returnTouchdowns": "0",
      "scoring_totalTouchdowns": "3",
      "scoring_totalTwoPointConvs": "0",
      "scoring_kickExtraPoints": "0",
      "scoring_fieldGoals": "0",
      "scoring_totalPoints": "18",
      "kicking_gamesPlayed": "17",
      "kicking_fieldGoalsMade-fieldGoalAttempts": "0-0",
      "kicking_fieldGoalPct": "0.0",
      "kicking_fieldGoalsMade1_19-fieldGoalAttempts1_19": "0-0",
      "kicking_fieldGoalsMade20_29-fieldGoalAttempts20_29": "0-0",
      "kicking_fieldGoalsMade30_39-fieldGoalAttempts30_39": "0-0",
      "kicking_fieldGoalsMade40_49-fieldGoalAttempts40_49": "0-0",
      "kicking_fieldGoalsMade50-fieldGoalAttempts50": "0-0",
      "kicking_longFieldGoalMade": "0",
      "kicking_extraPointsMade": "0",
      "kicking_extraPointAttempts": "0",
      "kicking_totalKickingPoints": "0"
    },
    {
      "Year": 2023,
      "Team": "las-vegas-raiders",
      "receiving_gamesPlayed": "17",
      "receiving_receptions": "4",
      "receiving_receivingTargets": "7",
      "receiving_receivingYards": "39",
      "receiving_yardsPerReception": "9.8",
      "receiving_receivingTouchdowns": "0",
      "receiving_longReception": "16",
      "receiving_receivingFirstDowns": "0",
      "receiving_receivingFumbles": "0",
      "receiving_receivingFumblesLost": "0",
      "rushing_gamesPlayed": "17",
      "rushing_rushingAttempts": "3",
      "rushing_rushingYards": "18",
      "rushing_yardsPerRushAttempt": "6.0",
      "rushing_rushingTouchdowns": "0",
      "rushing_longRushing": "15",
      "rushing_rushingFirstDowns": "2",
      "rushing_rushingFumbles": "0",
      "rushing_rushingFumblesLost": "0",
      "passing_gamesPlayed": "17",
      "passing_completions": "0",
      "passing_passingAttempts": "0",
      "passing_completionPct": "0.0",
      "passing_passingYards": "0",
      "passing_yardsPerPassAttempt": "0.0",
      "passing_passingTouchdowns": "0",
      "passing_interceptions": "0",
      "passing_longPassing": "0",
      "passing_sacks": "0",
      "passing_QBRating": "39.6",
      "passing_adjQBR": "-",
      "returning_gamesPlayed": "17",
      "returning_puntReturns": "24",
      "returning_puntReturnYards": "232",
      "returning_puntReturnTouchdowns": "0",
      "returning_puntReturnFairCatches": "18",
      "returning_longPuntReturn": "32",
      "returning_kickReturns": "11",
      "returning_kickReturnYards": "262",
      "returning_kickReturnTouchdowns": "0",
      "returning_kickReturnFairCatches": "0",
      "returning_longKickReturn": "40",
      "defensive_gamesPlayed": "N/A",
      "defensive_totalTackles": "N/A",
      "defensive_soloTackles": "N/A",
      "defensive_assistTackles": "N/A",
      "defensive_sacks": "N/A",
      "defensive_fumblesForced": "N/A",
      "defensive_fumblesRecovered": "N/A",
      "defensive_fumblesRecoveredYards": "N/A",
      "defensive_interceptions": "N/A",
      "defensive_interceptionYards": "N/A",
      "defensive_avgInterceptionYards": "N/A",
      "defensive_interceptionTouchdowns": "N/A",
      "defensive_longInterception": "N/A",
      "defensive_passesDefended": "N/A",
      "defensive_stuffs": "N/A",
      "defensive_stuffYards": "N/A",
      "defensive_kicksBlocked": "N/A",
      "scoring_gamesPlayed": "N/A",
      "scoring_passingTouchdowns": "N/A",
      "scoring_rushingTouchdowns": "N/A",
      "scoring_receivingTouchdowns": "N/A",
      "scoring_returnTouchdowns": "N/A",
      "scoring_totalTouchdowns": "N/A",
      "scoring_totalTwoPointConvs": "N/A",
      "scoring_kickExtraPoints": "N/A",
      "scoring_fieldGoals": "N/A",
      "scoring_totalPoints": "N/A",
      "kicking_gamesPlayed": "N/A",
      "kicking_fieldGoalsMade-fieldGoalAttempts": "N/A",
      "kicking_fieldGoalPct": "N/A",
      "kicking_fieldGoalsMade1_19-fieldGoalAttempts1_19": "N/A",
      "kicking_fieldGoalsMade20_29-fieldGoalAttempts20_29": "N/A",
      "kicking_fieldGoalsMade30_39-fieldGoalAttempts30_39": "N/A",
      "kicking_fieldGoalsMade40_49-fieldGoalAttempts40_49": "N/A",
      "kicking_fieldGoalsMade50-fieldGoalAttempts50": "N/A",
      "kicking_longFieldGoalMade": "N/A",
      "kicking_extraPointsMade": "N/A",
      "kicking_extraPointAttempts": "N/A",
      "kicking_totalKickingPoints": "N/A"
    },
    {
      "Year": 2024,
      "Team": "chicago-bears",
      "receiving_gamesPlayed": "2",
      "receiving_receptions": "4",
      "receiving_receivingTargets": "6",
      "receiving_receivingYards": "38",
      "receiving_yardsPerReception": "9.5",
      "receiving_receivingTouchdowns": "0",
      "receiving_longReception": "14",
      "receiving_receivingFirstDowns": "2",
      "receiving_receivingFumbles": "0",
      "receiving_receivingFumblesLost": "0",
      "rushing_gamesPlayed": "N/A",
      "rushing_rushingAttempts": "N/A",
      "rushing_rushingYards": "N/A",
      "rushing_yardsPerRushAttempt": "N/A",
      "rushing_rushingTouchdowns": "N/A",
      "rushing_longRushing": "N/A",
      "rushing_rushingFirstDowns": "N/A",
      "rushing_rushingFumbles": "N/A",
      "rushing_rushingFumblesLost": "N/A",
      "passing_gamesPlayed": "2",
      "passing_completions": "0",
      "passing_passingAttempts": "0",
      "passing_completionPct": "0.0",
      "passing_passingYards": "0",
      "passing_yardsPerPassAttempt": "0.0",
      "passing_passingTouchdowns": "0",
      "passing_interceptions": "0",
      "passing_longPassing": "0",
      "passing_sacks": "0",
      "passing_QBRating": "39.6",
      "passing_adjQBR": "-",
      "returning_gamesPlayed": "2",
      "returning_puntReturns": "6",
      "returning_puntReturnYards": "65",
      "returning_puntReturnTouchdowns": "0",
      "returning_puntReturnFairCatches": "1",
      "returning_longPuntReturn": "20",
      "returning_kickReturns": "3",
      "returning_kickReturnYards": "117",
      "returning_kickReturnTouchdowns": "0",
      "returning_kickReturnFairCatches": "0",
      "returning_longKickReturn": "67",
      "defensive_gamesPlayed": "N/A",
      "defensive_totalTackles": "N/A",
      "defensive_soloTackles": "N/A",
      "defensive_assistTackles": "N/A",
      "defensive_sacks": "N/A",
      "defensive_fumblesForced": "N/A",
      "defensive_fumblesRecovered": "N/A",
      "defensive_fumblesRecoveredYards": "N/A",
      "defensive_interceptions": "N/A",
      "defensive_interceptionYards": "N/A",
      "defensive_avgInterceptionYards": "N/A",
      "defensive_interceptionTouchdowns": "N/A",
      "defensive_longInterception": "N/A",
      "defensive_passesDefended": "N/A",
      "defensive_stuffs": "N/A",
      "defensive_stuffYards": "N/A",
      "defensive_kicksBlocked": "N/A",
      "scoring_gamesPlayed": "N/A",
      "scoring_passingTouchdowns": "N/A",
      "scoring_rushingTouchdowns": "N/A",
      "scoring_receivingTouchdowns": "N/A",
      "scoring_returnTouchdowns": "N/A",
      "scoring_totalTouchdowns": "N/A",
      "scoring_totalTwoPointConvs": "N/A",
      "scoring_kickExtraPoints": "N/A",
      "scoring_fieldGoals": "N/A",
      "scoring_totalPoints": "N/A",
      "kicking_gamesPlayed": "N/A",
      "kicking_fieldGoalsMade-fieldGoalAttempts": "N/A",
      "kicking_fieldGoalPct": "N/A",
      "kicking_fieldGoalsMade1_19-fieldGoalAttempts1_19": "N/A",
      "kicking_fieldGoalsMade20_29-fieldGoalAttempts20_29": "N/A",
      "kicking_fieldGoalsMade30_39-fieldGoalAttempts30_39": "N/A",
      "kicking_fieldGoalsMade40_49-fieldGoalAttempts40_49": "N/A",
      "kicking_fieldGoalsMade50-fieldGoalAttempts50": "N/A",
      "kicking_longFieldGoalMade": "N/A",
      "kicking_extraPointsMade": "N/A",
      "kicking_extraPointAttempts": "N/A",
      "kicking_totalKickingPoints": "N/A"
    }
  ]
}