{
  "statistics_by_year": [
    {
      "Year": 2022,
      "Team": "cleveland-browns",
      "defensive_gamesPlayed": "16",
      "defensive_totalTackles": "14",
      "defensive_soloTackles": "12",
      "defensive_assistTackles": "2",
      "defensive_sacks": "0",
      "defensive_fumblesForced": "0",
      "defensive_fumblesRecovered": "0",
      "defensive_fumblesRecoveredYards": "0",
      "defensive_interceptions": "0",
      "defensive_interceptionYards": "0",
      "defensive_avgInterceptionYards": "0.0",
      "defensive_interceptionTouchdowns": "0",
      "defensive_longInterception": "0",
      "defensive_passesDefended": "0",
      "defensive_stuffs": "0.5",
      "defensive_stuffYards": "0",
      "defensive_kicksBlocked": "0",
      "kicking_gamesPlayed": "N/A",
      "kicking_fieldGoalsMade-fieldGoalAttempts": "N/A",
      "kicking_fieldGoalPct": "N/A",
      "kicking_fieldGoalsMade1_19-fieldGoalAttempts1_19": "N/A",
      "kicking_fieldGoalsMade20_29-fieldGoalAttempts20_29": "N/A",
      "kicking_fieldGoalsMade30_39-fieldGoalAttempts30_39": "N/A",
      "kicking_fieldGoalsMade40_49-fieldGoalAttempts40_49": "N/A",
      "kicking_fieldGoalsMade50-fieldGoalAttempts50": "N/A",
      "kicking_longFieldGoalMade": "N/A",
      "kicking_extraPointsMade": "N/A",
      "kicking_extraPointAttempts": "N/A",
      "kicking_totalKickingPoints": "N/A"
    },
    {
      "Year": 2023,
      "Team": "cleveland-browns",
      "defensive_gamesPlayed": "17",
      "defensive_totalTackles": "28",
      "defensive_soloTackles": "25",
      "defensive_assistTackles": "3",
      "defensive_sacks": "0",
      "defensive_fumblesForced": "1",
      "defensive_fumblesRecovered": "0",
      "defensive_fumblesRecoveredYards": "0",
      "defensive_interceptions": "2",
      "defensive_interceptionYards": "8",
      "defensive_avgInterceptionYards": "4.0",
      "defensive_interceptionTouchdowns": "0",
      "defensive_longInterception": "6",
      "defensive_passesDefended": "4",
      "defensive_stuffs": "3",
      "defensive_stuffYards": "8",
      "defensive_kicksBlocked": "0",
      "kicking_gamesPlayed": "17",
      "kicking_fieldGoalsMade-fieldGoalAttempts": "0-0",
      "kicking_fieldGoalPct": "0.0",
      "kicking_fieldGoalsMade1_19-fieldGoalAttempts1_19": "0-0",
      "kicking_fieldGoalsMade20_29-fieldGoalAttempts20_29": "0-0",
      "kicking_fieldGoalsMade30_39-fieldGoalAttempts30_39": "0-0",
      "kicking_fieldGoalsMade40_49-fieldGoalAttempts40_49": "0-0",
      "kicking_fieldGoalsMade50-fieldGoalAttempts50": "0-0",
      "kicking_longFieldGoalMade": "0",
      "kicking_extraPointsMade": "0",
      "kicking_extraPointAttempts": "0",
      "kicking_totalKickingPoints": "0"
    }
  ]
}