{
  "statistics_by_year": [
    {
      "Year": 2021,
      "Team": "new-york-giants",
      "receiving_gamesPlayed": "10",
      "receiving_receptions": "39",
      "receiving_receivingTargets": "57",
      "receiving_receivingYards": "420",
      "receiving_yardsPerReception": "10.8",
      "receiving_receivingTouchdowns": "0",
      "receiving_longReception": "38",
      "receiving_receivingFirstDowns": "21",
      "receiving_receivingFumbles": "0",
      "receiving_receivingFumblesLost": "0",
      "rushing_gamesPlayed": "10",
      "rushing_rushingAttempts": "3",
      "rushing_rushingYards": "6",
      "rushing_yardsPerRushAttempt": "2.0",
      "rushing_rushingTouchdowns": "0",
      "rushing_longRushing": "7",
      "rushing_rushingFirstDowns": "0",
      "rushing_rushingFumbles": "0",
      "rushing_rushingFumblesLost": "0",
      "passing_gamesPlayed": "10",
      "passing_completions": "1",
      "passing_passingAttempts": "3",
      "passing_completionPct": "33.3",
      "passing_passingYards": "19",
      "passing_yardsPerPassAttempt": "6.3",
      "passing_passingTouchdowns": "0",
      "passing_interceptions": "0",
      "passing_longPassing": "19",
      "passing_sacks": "1",
      "passing_QBRating": "56.3",
      "passing_adjQBR": "2.3",
      "returning_gamesPlayed": "10",
      "returning_puntReturns": "1",
      "returning_puntReturnYards": "0",
      "returning_puntReturnTouchdowns": "0",
      "returning_puntReturnFairCatches": "1",
      "returning_longPuntReturn": "0",
      "returning_kickReturns": "0",
      "returning_kickReturnYards": "0",
      "returning_kickReturnTouchdowns": "0",
      "returning_kickReturnFairCatches": "0",
      "returning_longKickReturn": "0",
      "scoring_gamesPlayed": "N/A",
      "scoring_passingTouchdowns": "N/A",
      "scoring_rushingTouchdowns": "N/A",
      "scoring_receivingTouchdowns": "N/A",
      "scoring_returnTouchdowns": "N/A",
      "scoring_totalTouchdowns": "N/A",
      "scoring_totalTwoPointConvs": "N/A",
      "scoring_kickExtraPoints": "N/A",
      "scoring_fieldGoals": "N/A",
      "scoring_totalPoints": "N/A"
    },
    {
      "Year": 2022,
      "Team": "new-york-giants",
      "receiving_gamesPlayed": "7",
      "receiving_receptions": "14",
      "receiving_receivingTargets": "17",
      "receiving_receivingYards": "171",
      "receiving_yardsPerReception": "12.2",
      "receiving_receivingTouchdowns": "2",
      "receiving_longReception": "38",
      "receiving_receivingFirstDowns": "8",
      "receiving_receivingFumbles": "0",
      "receiving_receivingFumblesLost": "0",
      "rushing_gamesPlayed": "7",
      "rushing_rushingAttempts": "5",
      "rushing_rushingYards": "59",
      "rushing_yardsPerRushAttempt": "11.8",
      "rushing_rushingTouchdowns": "1",
      "rushing_longRushing": "32",
      "rushing_rushingFirstDowns": "4",
      "rushing_rushingFumbles": "0",
      "rushing_rushingFumblesLost": "0",
      "passing_gamesPlayed": "7",
      "passing_completions": "0",
      "passing_passingAttempts": "0",
      "passing_completionPct": "0.0",
      "passing_passingYards": "0",
      "passing_yardsPerPassAttempt": "0.0",
      "passing_passingTouchdowns": "0",
      "passing_interceptions": "0",
      "passing_longPassing": "0",
      "passing_sacks": "0",
      "passing_QBRating": "39.6",
      "passing_adjQBR": "20.4",
      "returning_gamesPlayed": "7",
      "returning_puntReturns": "10",
      "returning_puntReturnYards": "61",
      "returning_puntReturnTouchdowns": "0",
      "returning_puntReturnFairCatches": "4",
      "returning_longPuntReturn": "9",
      "returning_kickReturns": "0",
      "returning_kickReturnYards": "0",
      "returning_kickReturnTouchdowns": "0",
      "returning_kickReturnFairCatches": "0",
      "returning_longKickReturn": "0",
      "scoring_gamesPlayed": "7",
      "scoring_passingTouchdowns": "0",
      "scoring_rushingTouchdowns": "1",
      "scoring_receivingTouchdowns": "2",
      "scoring_returnTouchdowns": "0",
      "scoring_totalTouchdowns": "3",
      "scoring_totalTwoPointConvs": "0",
      "scoring_kickExtraPoints": "0",
      "scoring_fieldGoals": "0",
      "scoring_totalPoints": "18"
    },
    {
      "Year": 2023,
      "Team": "kansas-city-chiefs",
      "receiving_gamesPlayed": "13",
      "receiving_receptions": "27",
      "receiving_receivingTargets": "38",
      "receiving_receivingYards": "169",
      "receiving_yardsPerReception": "6.3",
      "receiving_receivingTouchdowns": "1",
      "receiving_longReception": "18",
      "receiving_receivingFirstDowns": "12",
      "receiving_receivingFumbles": "1",
      "receiving_receivingFumblesLost": "0",
      "rushing_gamesPlayed": "13",
      "rushing_rushingAttempts": "11",
      "rushing_rushingYards": "31",
      "rushing_yardsPerRushAttempt": "2.8",
      "rushing_rushingTouchdowns": "0",
      "rushing_longRushing": "14",
      "rushing_rushingFirstDowns": "2",
      "rushing_rushingFumbles": "0",
      "rushing_rushingFumblesLost": "0",
      "passing_gamesPlayed": "13",
      "passing_completions": "0",
      "passing_passingAttempts": "1",
      "passing_completionPct": "0.0",
      "passing_passingYards": "0",
      "passing_yardsPerPassAttempt": "0.0",
      "passing_passingTouchdowns": "0",
      "passing_interceptions": "0",
      "passing_longPassing": "0",
      "passing_sacks": "0",
      "passing_QBRating": "39.6",
      "passing_adjQBR": "0.4",
      "returning_gamesPlayed": "13",
      "returning_puntReturns": "6",
      "returning_puntReturnYards": "58",
      "returning_puntReturnTouchdowns": "0",
      "returning_puntReturnFairCatches": "0",
      "returning_longPuntReturn": "21",
      "returning_kickReturns": "0",
      "returning_kickReturnYards": "0",
      "returning_kickReturnTouchdowns": "0",
      "returning_kickReturnFairCatches": "0",
      "returning_longKickReturn": "0",
      "scoring_gamesPlayed": "13",
      "scoring_passingTouchdowns": "0",
      "scoring_rushingTouchdowns": "0",
      "scoring_receivingTouchdowns": "1",
      "scoring_returnTouchdowns": "0",
      "scoring_totalTouchdowns": "1",
      "scoring_totalTwoPointConvs": "0",
      "scoring_kickExtraPoints": "0",
      "scoring_fieldGoals": "0",
      "scoring_totalPoints": "6"
    }
  ]
}